ChatCAT/__init__.py
ChatCAT/main.py
ChatCAT-1.0.1.dist-info/METADATA
ChatCAT-1.0.1.dist-info/WHEEL
ChatCAT-1.0.1.dist-info/top_level.txt
ChatCAT-1.0.1.dist-info/RECORD
