Metadata-Version: 2.1
Name: ChatCAT
Version: 1.0.1
Summary: chatbot
Author: RGB_CATT
Author-email: 
Keywords: python,chat,bot,chatbot,chatting robot
Classifier: Development Status :: 1 - Planning
Classifier: Intended Audience :: Developers
Classifier: Programming Language :: Python :: 3
Classifier: Operating System :: Unix
Classifier: Operating System :: MacOS :: MacOS X
Classifier: Operating System :: Microsoft :: Windows
Requires-Dist: typing
